easyprep/__init__.py
easyprep/core.py
easyprep/models/lin_reg.py
easyprep/preprocess/__init__.py
easyprep/preprocess/encoder.py
easyprep/preprocess/nan_handler.py
easyprep/preprocess/outlier_handler.py
easyprep/preprocess/scaler.py
easyprep/preprocess/skew_handler.py
ez_easyprep-1.1.0.dist-info/METADATA
ez_easyprep-1.1.0.dist-info/WHEEL
ez_easyprep-1.1.0.dist-info/top_level.txt
ez_easyprep-1.1.0.dist-info/RECORD
