Metadata-Version: 2.4
Name: ez-easyprep
Version: 1.1.0
Summary: Simple data preprocessing utilities for tabular data
Author-email: Hassan Rasheed <craftycode121@gmail.com>
License: MIT
Keywords: data-preprocessing,ml,tabular-data
Classifier: Programming Language :: Python :: 3
Classifier: License :: OSI Approved :: MIT License
Classifier: Operating System :: OS Independent
Classifier: Topic :: Scientific/Engineering :: Artificial Intelligence
Classifier: Intended Audience :: Developers
Requires-Python: >=3.9
Requires-Dist: numpy>=1.4
